[
  {
    "381": "Коньяк АРАРАТ 3 звезды армян.40% 0.5л",
    "383": "Коньяк АРМЯНСК.АНИ 6лет п/у 40% 0.5л",
    "1272": "Ликер BAILEYS 17%          0.5л",
    "1281": "Вермут CINZANO BIANCO бел.сл. 1.0л",
    "1306": "Водка СТОЛИЧНАЯ 40% 0.5л",
    "1312": "Водка ПРАЗДНИЧНАЯ 40% 0.5л",
    "1326": "Ликер БЕХЕРОВКА горький 38% 0.5л",
    "1349": "Виски JOH.WALKER red       0.5л",
    "1369": "Водка FINLANDIA  40% 0.5л",
    "1373": "Водка ABSOLUT 40% 0.5л",
    "1378": "Текила OLMECA BLANCO 38%   1.0л",
    "1400": "Джин BEEFEATER LONDON DRY 47% фляж.0.5л",
    "1425": "Нап.Спир.METAXA 7*п/уп 40% 0.7л",
    "5299": "Коньяк СТ.КЕНИГСБЕРГ рос.4г 40% фл.0.25л",
    "6217": "Ром BACARDI SUPERIOR 40% 0.75л",
    "6348": "Коньяк МОСКОВСКИЙ четырехлетний 40% 0.5л",
    "6801": "Коньяк MARTELL VSOP MED.40% 0.5л",
    "7718": "Виски CHIVAS REGAL 40% п/у 0.375л",
    "7875": "Водка СТАРАЯ МОСКВА гуала 40% 0.5л",
    "7905": "Водка ПОСОЛЬСКАЯ 40% 0.5л",
    "7949": "Коньяк 3 ЗВЕЗДОЧКИ рос.3года 40% 0.5л",
    "8084": "Наст.РЯБИН.на коньяке сладк.24% 0.5л",
    "9597": "Виски WHITE HORSE 40%    0.35л",
    "11194": "Ром HAVANA CLUB 40% 3года  0.7л",
    "12091": "Виски BALLANTINES FINEST 40% 0.5л",
    "12105": "Коньяк COURVOISIER VS п/у 40%0.5л",
    "13185": "Коньяк MARTELL VSOP п/у 40% 0.35л",
    "14051": "Бренди ТОРРЕС Cолера Рез5лет38% п/у 0.7л",
    "14969": "Водка ЛАДОГА ЦАРСКАЯ 40% 1.0л",
    "15389": "Виски BALLANTINE FINEST 40% 1.0л",
    "15390": "Виски CHIVAS REGAL 12лет 40% п/у 0.5л",
    "15740": "Виски GRANTS 40% треуг.   0.5л",
    "17898": "Шамп.M&C.Brut Imp.12% п/у  0.75л",
    "17989": "Коньяк HENNESSY VS 40% п/у 0.7л",
    "17990": "Коньяк HENNESSY VSOP п/у 40% 0.35л",
    "17992": "Коньяк HENNESSY XO 40% п/у 0.7л",
    "18002": "Виски TULLAMORE DEW 40% 0.7л",
    "18104": "Водка АРБАТСКАЯ ЭЛИТ.гуал.40% 0.5л",
    "18583": "Коньяк HENNESSY VSOP 40% 0.5л",
    "19050": "Напиток спиртовой METAXA 5* п/у 38% 0.7л",
    "19829": "Коньяк HENNESSY XO 40% п/у 0.35л",
    "22924": "Коньяк Ст.Кенигсберг Рос.4летн.40% 0.5л",
    "23362": "Коньяк REMY MARTIN VSOP 40% п/у 0.5л",
    "23407": "Ликер COINTREAU крепкий 40% 0.5л",
    "24395": "Коньяк COURVOISIER VSOP п/у 40% 0.5л",
    "26505": "Виски FAMOUS GROUSE 40%    0.5л",
    "26510": "Ликер ЯГЕРМАЙСТЕР десертный 35% 0.7л",
    "27652": "Ликер КАМПАРИ десертный 25% 0.5л",
    "29238": "Вермут CINZANO BIANCO 15% 0.5л",
    "32595": "Виски JAMESON ирландское 40% 0.7л",
    "36862": "Коньяк HENNESSY VSOP п/у 40% 0.7л",
    "39112": "Водка СТАРАЯ МОСКВА 40% 0.7л",
    "39121": "Водка БЕЛАЯ БЕРЕЗКА 40% 0.5л",
    "39490": "Бренди TORRES Гран Рез.10 38%п/у 0.7л",
    "40804": "Водка СЛАВЯН.РЖАН.ИЗ ОТБ.РЖИ ос.40% 0.5л",
    "41381": "Водка ЗЕЛ.МАРКА КЕДР.особ.40% 0.5л",
    "46906": "Ликер ЯГЕРМАЙСТЕР десерт.35% 0.5л",
    "56573": "Водка МЯГКОВ СЕРЕБРЯНАЯ 40% 0.5л",
    "57453": "Коньяк ТРОФЕЙНЫЙ 4года фл.росс.40% 0.5л",
    "57454": "Коньяк СТАР.КЕН.4г.п/у россий.40% 0.5л",
    "57459": "Водка ПРАЗДНИЧНАЯ 40%     0.25л",
    "57647": "Водка РУССКИЙ СТАНДАРТ 40% 0.5л",
    "57648": "Водка РУССКИЙ СТАНДАРТ 40% 1.0л",
    "58107": "Ликер БЕХЕРОВКА десертный 38% 0.7л",
    "62439": "Виски TULLAMORE DEW 12л.п/у 40% 0.7л",
    "62634": "Коньяк НОЙ АРАСПЕЛ арм.5зв.40% п/у 0.5л",
    "62641": "Коньяк НОЙ КЛАССИК арм.7лет 40% п/у 0.5л",
    "63440": "Водка РУССКИЙ СТАНДАРТ п/уп 40% 0.5л",
    "65286": "Виски GRANTS 12л 40% п/у 0.75л",
    "66957": "Водка ПУТИНКА классическая 40% 0.5л",
    "68525": "БальзамРИЖСКИЙчерн.кувш45% 0.5л",
    "69024": "Виски JIM BEAM BOURBON 40% 0.7л",
    "71223": "Водка РУС.БРИЛ.PREMIUM син.эт.40% 0.5л",
    "71818": "Текила SAUZA SILVER 38%    0.5л",
    "73459": "Водка БЕЛОЕ ЗОЛОТО 40% 0.5л",
    "80185": "Коньяк REM.MART.ХО ЕХ.40% п/у 0.35л",
    "84708": "Водка ЗЕЛ.МАРКА Трад.рецептура 40% 0.7л",
    "84889": "Водка БЕЛЕНЬКАЯ ЛЮКС 40% 0.5л",
    "84890": "Водка БЕЛЕНЬКАЯ ЗОЛОТАЯ 40% 0.5л",
    "87880": "Водка РУССКИЙ СТАНДАРТ ПЛАТИНУМ 40% 0.5л",
    "88247": "Водка ПАРЛАМЕНТ КЛАССИК 40% 0.7л",
    "88251": "Водка ПАРЛАМЕНТ 40% 0.5л",
    "88888": "Портвейн ПОРТО АЛЕГРЕ РУБИ кр. 0.75л",
    "91293": "Ликёр MALIBU COCONUT 21%   1.0л",
    "96215": "Настойка ПЕРЦОВ.гор.35% фл.0.5л",
    "97315": "Водка ЗЕЛ.МАРКА традиц.40% 0.5л",
    "99234": "Виски FAMOUS GROUSE SCOTCH 40% 0.7л",
    "2026135": "Настойка ЛАДОГА КЛЮКВЕН.слад.20% 0.5л",
    "2031291": "Наливка АЛКОН СПОТЫКАЧ 20% 0.5л",
    "2038674": "Коньяк АПШЕРОН российский 4год 40% 0.5л",
    "2039285": "Водка УСАДСКАЯ 40% хлебная 0.5л",
    "2039569": "Водка ПЯТЬ ОЗЕР 40% 0.7л",
    "2039570": "Водка ПЯТЬ ОЗЕР 40% 0.5л",
    "2039572": "Водка ПЯТЬ ОЗЕР 40% 1.0л",
    "2041037": "Водка ЗЕЛЕНАЯ МАРКА КЕДР.особ.40% 0.7л",
    "2046527": "Джин ВЕРЕСК ст/б       0.7л",
    "2046823": "Водка БЕЛЕНЬКАЯ люкс фл.40% 0.25л",
    "2047168": "Водка БЕЛУГА НОБЛ 40% 0.5л",
    "2048005": "Виски DEWARS WHITE LABEL 40% 0.5л",
    "2048006": "Виски DEWARS SP.RES.40% п/у 0.5л",
    "2050466": "Водка ЭТАЛОН 40% 0.5л",
    "2053745": "Водка ЦАРСКАЯ ЗОЛОТАЯ 40% 0.5л",
    "2053835": "Водка ЦАРСКАЯ ОРИГИНАЛЬНАЯ 40% 0.5л",
    "2060701": "Водка ВЫСОТА ЛЮКС ПРЕМ.40% 0.5л",
    "2064056": "Коньяк СТАР.КЕНИГСБ.КВ РОС.40% 0.5л",
    "2064058": "Виски ДЖЕК ДЕНИЕЛС 40%    0.5л",
    "2064067": "Ром BACARDI GOLD 40% 0.75л",
    "2064131": "Нап.Спир.METAXA 5* 38% 0.5л",
    "2065343": "Коньяк КИНОВСКИЙ 3года росс.40% 0.25л",
    "2065344": "Коньяк КИНОВСКИЙ росс.3года 40% 0.5л",
    "2069099": "Виски JAMESON 40%          0.5л",
    "2069112": "Настойка ТРИ СТАРИКА гор.40% 0.5л",
    "2082147": "Водка ЖУРАВЛИ 40% 0.5л",
    "2088589": "Водка РУССКИЙ ЛЕД 40% 0.5л",
    "2088746": "Настойка ЭТАЛОН КЕДР горькая 40% 0.5л",
    "2097694": "Водка МОСКОВСКАЯ ОСОБАЯ 40% 0.5л",
    "2104197": "Водка ГОСУДАРЕВ ЗАКАЗ штоф 40% 0.5л",
    "2106571": "Ликер SHERID.коф.2-сл. 15,5% 0.5л",
    "2107196": "Нап.вин.АКУРА БЕЛ.аром.со вк.сливы 0.75л",
    "2120745": "Коньяк АРМЯНСКИЙ 5* 40% 0.5л",
    "2120749": "Виски КЛАН МАК ГРЕГОР 40% 0.5л",
    "2121923": "Настойка ТРИ СТАРИКА гор.40% 0.25л",
    "2123514": "Аперитив СТЕПНОЙ ВЕТЕР 18% 0.5л",
    "2124133": "Водка СМИРНОВ №21 40% 0.5л",
    "2137723": "Вермут МАРТИНИ БЬЯНКО сл.бел.15% 1.0л",
    "2137724": "Верм.МАРТИНИ БЬЯНКО сл.бел.0.5л",
    "2137725": "Верм.МАРТИНИ РОССО сл.кр.15% 1.0л",
    "2137727": "Верм.МАРТИНИ РОССО сл.кр.15% 0.5л",
    "2137730": "Верм.МАРТИНИ РОЗАТО сл.роз.15% 1.0л",
    "2137743": "Верм.МАРТИНИ ЭКСТ.ДРАЙ бел.сух.18% 0.5л",
    "2138458": "Текила ТРЕС САМБРЕРОС БЕЛАЯ 38% 0.7л",
    "2142197": "Коньяк РОСС.ЗОЛ.ВЫД.5ЗВЕЗД.40% 0.5л",
    "2144518": "Коньяк REMY MARTIN VS СУПЕР.40% п/у 0.5л",
    "2150157": "Водка ПУТИНКА МЯГКАЯ классическ.40% 0.5л",
    "2155446": "Водка ПЯТЬ ОЗЕР 40% 0.25л",
    "2161005": "Виски GLENMORANGIE 40% 10лет п/у 0.7л",
    "2161035": "Коньяк РОССИЙКИЙ УСОВСКИЙ 3зв.40% 0.5л",
    "2162216": "Водка СТАР.МОСКВА ШИПОВН.гуала 40% 0.5л",
    "2162387": "Водка ЦАРСКАЯ оригин 40%   0.7л",
    "2163059": "Наст.СОРМ.КЛЮКВ/КОНЬЯК 21% 0.5л",
    "2163682": "Коньяк СТ.КЕНИГСБЕРГ росс.5лет.40% 0.5л",
    "2163885": "Водка МЕРНАЯ НА МОЛОКЕ 40% 0.5л",
    "2173695": "Водка ТРИ РЕКИ ЧИСТАЯ 40% 0.5л",
    "3002175": "Водка МЕДОФФ ЛЮКС 40% 0.5л",
    "3048019": "Виски Бушмиллс Блэк Буш п/у 40% 0.7л",
    "3053979": "Водка РУССКОЕ ЗОЛОТО 40% 0.5л",
    "3063386": "Коньяк КиНовский 3* фляжка 40% 0.1л",
    "3070199": "Водка ГОСУДАРЕВ ЗАКАЗ 40% 1.0л",
    "3070469": "Ром БАРСЕЛО АНЬЕХА темный выд.37,5% 0.7л",
    "3130857": "Водка ЦАРСКАЯ ЗОЛОТАЯ+2ст.40%п/у 0.7л",
    "3148871": "Виски BUSHMILLS Ориг.40%п/у 0.7л",
    "3159579": "Водка РУССКИЙ СТАНДАРТ ГОЛД 40% 0.5л",
    "3166627": "Виски WHITE HORSE 40% 0.5л",
    "3169740": "Водка ПЯТЬ ОЗЕР ПРЕМИУМ 40% 0.5л",
    "3169747": "Водка КЕДРОВИЦА кедровый орех 40% 0.5л",
    "3171928": "Наст.БУЛЬБАШ ЗУБРОВАЯ 40% 0.5л",
    "3171929": "Наст.БУЛЬБАШ КЛЮКВЕННАЯ40% 0.5л",
    "3171931": "Наст.БУЛЬБАШ МЕД/ПЕРЕЦ 40% 0.5л",
    "3184359": "Напит.BOSCA ROSE роз.п/сл.газ.7,5% 0.75л",
    "3194597": "Водка БАЙКАЛ 40% 0.5л",
    "3196438": "Виски БЭЛЛС ОРИДЖИНАЛ 40% 0.7л",
    "3199166": "Водка МЯГКИЙ ЗНАК КЛАССИК 40% 0.5л",
    "3212623": "Коньяк СТАРЕЙШИНА КВ 7лет 40% 0.5л",
    "3229277": "Виски ГРАНТС ФАМИЛИ РЕЗЕРВ 40% 0.75л",
    "3229289": "Виски ГЛЕНФИДДИК 12лет 40% тубус 0.5л",
    "3229294": "Виски ГЛЕНФИДДИК 12лет 40% тубус 0.75л",
    "3231408": "Виски Бурбон МЭЙКЕРС МАРК 45% 0.7л",
    "3232198": "Виски БЭЛЛС ОРИДЖИНАЛ 40% 0.5л",
    "3232203": "Нап.Ром КАП.МОРГАН ПРЯН.ЗОЛ.35% 0.5л",
    "3234684": "Напиток Вермут MARTIAMO Бьянко вин.1.0л",
    "3245596": "Коньяк БЕСТУЖЕВ КЛАССИК 5лет 40% 0.5л",
    "3245992": "Водка СТАРАЯ МАРКА КЛАССИЧЕСКАЯ 40% 0.5л",
    "3246592": "Водка СЛОБОДА классическая 40% 0.5л",
    "3247206": "Виски БАЛЛАНТАЙЗ ФАЙНЕСТ 40% 0.7л",
    "3247213": "Виски БАЛЛАНТАЙЗ ФАЙНЕСТ 40% п/у 0.7л",
    "3247216": "Виски ЧИВАС РИГАЛ 12лет 40% п/у 0.7л",
    "3247323": "Коньяк СТАРЕЙШИНА 5лет 40% 0.5л",
    "3248852": "Текила ОЛЬМЕКА БЕЛАЯ 38% 0.7л",
    "3250959": "Водка ТРИУМФ 40% 0.25л",
    "3255059": "Ликер МАЛИБУ на основе рома 21% 0.7л",
    "3255231": "Ликер АМАРЕТТО САН МАРКО десерт.25% 0.5л",
    "3258283": "Водка ЦАРЬ КЕДР 40% 0.5л",
    "3262462": "Коньяк ЗОЛОТОЙ РЕЗЕРВ рос.5лет 42% 0.5л",
    "3272512": "Водка БУЛЬБАШЪ ОСОБАЯ 40% 0.5л",
    "3273316": "Текила ОЛЬМЕКА ЗОЛОТАЯ СУПРЕМО 38% 0.7л",
    "3282705": "Водка ЗИМНЯЯ ДОРОГА 40% 0.5л",
    "3290386": "Водка ЗИМНЯЯ ДОРОГА Ночная 40% 0.5л",
    "3294789": "Настойка АБСОЛЮТ КУРАНТ горькая 40% 0.7л",
    "3294804": "Водка АБСОЛЮТ 40% 0.7л",
    "3298929": "Виски ДЖ.УОКЕР РЭД ЛЕЙБЛ 40% п/у 0.7л",
    "3298945": "CAP.MORG.Нап.ПР.ЗОЛ.на осн.рома35% 0.7л",
    "3298986": "Вино ЗОНИН РОЗЕ игр.розов.брют 11% 0.75л",
    "3299178": "Ликер БЭЙЛИС слив.ориг.17% 0.7л",
    "3300134": "Коньяк АРМ.АРАРАТ 5* арм.40% п/у 0.5л",
    "3301325": "Водка ГРАФ ЛЕДОФФ 40% 0.5л",
    "3306455": "Водка ПЯТЬ ОЗЕР ОСОБАЯ 40% 0.5л",
    "3306456": "Водка ПЯТЬ ОЗЕР ОСОБАЯ 40% 0.7л",
    "3307830": "Водка КАЛИНКА ХОХЛОМА 40% 0.5л",
    "3326055": "Виски WHITE HORSE шотл.3г 40% п/у 0.7л",
    "3327690": "Коньяк РОССИЙСКИЙ 5* пятилет.40% 0,5л",
    "3329248": "Ликер ИСТ.ЛЮБВИ СЛИВ.ВКУС эмул.18% 0.5л",
    "3331217": "Виски СИНГ.В.ДАФ.12л шотл.однос.40% 0.7л",
    "3331496": "Водка СТАРАЯ МОСКВА 40% 0.25л",
    "3331963": "Водка FINNORD 40% 0.5л",
    "3331968": "Водка FINNORD ОСОБАЯ КЛЮКВЕННАЯ 40% 0.5л",
    "3332415": "Виски БАЛЛАНТАЙНС 12лет 40% п/у 0.7л",
    "3332431": "Коньяк 5 ЗВЕЗДОЧЕК рос.5 лет 40% 0.5л",
    "3332434": "Коньяк ЛЕЗГИНКА рос.КВ 40% 0.5л",
    "3332678": "Бальзам КАРЕЛЬСКИЙ 45% 0.5л",
    "3336405": "Водка КАЛИНКА ЭКСПОРТ 40% 0.5л",
    "3337311": "Водка БРЯНСК ЛЮКС 40% 0.25л",
    "3337323": "Водка ТРИ КАПЛИ 40% 0.25л",
    "3346620": "Водка ТАЛКА 40% 0.5л",
    "3349140": "Коньяк РУС.МАНЕРЪ росс.четырехл.0.5л",
    "3349146": "Коньяк РУС.МАНЕРЪ рос.четырехл.40% 0.25л",
    "3350067": "Коньяк ДЖИГИТ РОССИЙСКИЙ трехл.40% 0.5л",
    "3350075": "Коньяк ДЖИГИТ РОССИЙСКИЙ пятил.40% 0.5л",
    "3350079": "Коньяк ДЖИГИТ РОСС.выдержанн.КВ 40% 0.5л",
    "3351881": "Виски ВИЛЬЯМ ЛОУСОНС 40% 0.5л",
    "3352192": "Водка Кизлярка Традиц.виноград.40% 0.5л",
    "3352441": "Водка Рус.Север Традиционная 40% 0.5л",
    "3353297": "Водка ХАСКИ 40% 0.5л",
    "3355026": "Вино ПРЕМ.РОЗ.игр.выд.брют 11-13% 0.75л",
    "3355244": "Ром BACARDI BLACK 40% п/у+3 шота 0.75л",
    "3355902": "Коньяк ДЖИГИТ РОССИЙ.выдерж.п/у 40% 0.5л",
    "3357140": "Коньяк РОССИЙСКИЙ 5* 5лет 40% 0.5л",
    "3357378": "Коньяк РОССИЙСКИЙ 3* 3года 40% 0.5л",
    "3358031": "Коньяк АРМ.№3 СТР.КАМНЕЙ 3года 40% 0.5л",
    "3358032": "Коньяк АРМ.№5 СТР.КАМНЕЙ 5лет 40% 0.5л",
    "3358840": "Водка ДОБРЫЙ МЕДВЕДЬ 40% 0.5л",
    "3359008": "Водка DROVA очищ.березов.углем 40% 0.5л",
    "3359191": "Виски ДЖОН.УОКЕР Блэк Л.12л43% п/у 0.5л",
    "3359549": "Виски JACK DANIELS Теннесси 40% 0.7л",
    "3364571": "Водка KREMLIN AWARD 40% 0.5л",
    "3364579": "Коньяк БАГРАТ армянский 3 года 0.5л",
    "3364581": "Коньяк БАГРАТ армянский 5 лет 40% 0.5л",
    "3370435": "Виски PASSPORT SCOTCH 40% 0.5л",
    "3373834": "Шамп.РОС.АБРАУ-ДЮРС.роз.п.с.с.9-15 0.75л",
    "3375216": "Коньяк 5 ЗВЕЗДОЧЕК РОС.пятилет.0.25л",
    "3377304": "Водка КАЛИНА КРАСНАЯ 40% 0.25л",
    "3377938": "Коньяк АРМЯНСКИЙ пятилетний 40% 0.5л",
    "3379495": "Водка ТАЛКА 40% 0.7л",
    "3381026": "Виски JACK DANIELS Тен.мет.п/у+2ст.0.7л",
    "3381059": "Напиток Вермут SANTANELLI вин.бел.1.0л",
    "3381538": "Коньяк БАРКЛАЙ ДЕ ТОЛ.Росс.5лет.40% 0.5л",
    "3382457": "Напиток КАГОР32 Десерт.винный 16% 0.7л",
    "3382992": "Нап.ПОЛУГ.№1 Рожь/Пш.спир.алк.38,5% 0.5л",
    "3383747": "Виски DOUBLE TOWER 40% 0.7л",
    "3385230": "Водка ЖУРАВЛИ серебряная 40% 0.5л",
    "3385245": "Водка ЗЕЛЕНАЯ МАРКА КЕДР.особ.40% 0.375л",
    "3385926": "Водка МОРОША на мин.воде мяг.1 40% 0.5л",
    "3385934": "Водка МОРОША на мин.воде мяг.2 40% 0.5л",
    "3386430": "Бренди ДЕРБЕНТСКАЯ КРЕПОСТЬ 0.5л",
    "3386752": "Коньяк КИНОВСКИЙ российск.5лет 40% 0.5л",
    "3388229": "Нап.вин.КАГОР МОН.АМУЛЕТ  0.7л",
    "3388230": "Нап.вин.ПОРТВЕЙН ВИНОГОР кр. 0.7л",
    "3396359": "Водка РУССКАЯ ВАЛЮТА ПЛАТИНУМ 40% 0.5л",
    "3396443": "Виски БИЛЛ МАКЛИН купажир.40% 0.7л",
    "3397914": "Водка НАСТОЯЩАЯ ПЛАТИНОВАЯ 40% 0.5л",
    "3398930": "Нап.спирт.Аперитив АПЕРОЛЬ 11% 0.7л",
    "3403868": "Коньяк НАСЛ.МАСТ.ЛЕВЪ ГОЛИЦ.4г.40% 0.5л",
    "3405058": "Виски ВИЛЬЯМ ЛОУСОНС 13 лет 40% 0.75л",
    "3405362": "Коньяк HENNESSY VS в п/у 40% 0.5л",
    "3405364": "Коньяк HENNESSY VS в п/у 40% 0.35л",
    "3405566": "Бальзам СТАРЫЙ ТРАВНИК 40% 0.5л",
    "3405617": "Вино АНЖЕЛ.ЛАМБР.ЭМ.игр.кр.п/сл 0.75л",
    "3405618": "Вино АНЖЕЛ.ЛАМБР.ЭМ.игр.роз.п/сл 0.75л",
    "3406172": "Водка КАЛИНА КРАСНАЯ 40% 0.5л",
    "3406372": "Водка БЕЛЕНЬКАЯ ЛЮКС 40% 0.7л",
    "3406799": "Текила РАНЧО ВЬЕХО СИЛЬВЕР  0.7л",
    "3406801": "Коньяк СТАРЫЙ КЕНИГСБЕРГ 4года 40% 0.7л",
    "3407018": "Виски SCOTTISH LAND 40% 0.7л",
    "3407669": "Бальзам БУГУЛЬМА винт фляга 40% 0.5л",
    "3408073": "Водка ГРАФ БУТУРЛИН поход.особ.40% 0.25л",
    "3408128": "Водка ФИНСКИЙ ЛЕД 40% 0.5л",
    "3409296": "Коньяк ТРАД.МОЛД.РОССИЙС.пятил.40%0.5л",
    "3409399": "Водка ФИНЛЯНДИЯ 40% п/у 0.7л+2 рюмки",
    "3409426": "Напиток ДЖЕК ДЕНИЕЛС ХАНИ ЛИКЕР 35% 0.7л",
    "3409471": "Виски BUSHMILLS ORIGINAL п/у40% 0.7л+2ст",
    "3409472": "Напиток РЭД СТАГ БЛЭК ЧЕРРИ 40% 0.7л",
    "3409599": "Виски GRANTS FAMILY RES.п/у40% 0.75л+2б.",
    "3409677": "Ликер ЯГЕРМАЙСТЕР дес.п/у 35% 0.7л+фляга",
    "3412336": "Коньяк FATHER.OLD BARREL РОС.5л 40% 0.5л",
    "3412468": "Коньяк MONTE CHOCO РОС.пятилет.40% 0.5л",
    "3414136": "Виски SCOTTISH LAND шотл.купаж.40% 0.35л",
    "3414155": "Виски ТИЧЕРС ХАЙЛАНД КРИМ 40% п/у 0.7л",
    "3414902": "Водка ЗИМНЯЯ ДОРОГА 40% 0.7л",
    "3414975": "Водка СТОПАРИК 40% 0.1л",
    "3415861": "Водка ЦЕЛЬСИЙ КЛАССИК 40% 0.5л",
    "3415864": "Водка ЦЕЛЬСИЙ ЛАЙТ особая 40% 0.5л",
    "3416158": "Текила OLMECA GOLD 38% п/у с 2 шот. 0.7л",
    "3417394": "Водка ЯРИЦА 40% 0.5л",
    "3417626": "Коньяк РОССИЙСК.ДАГЕСТАН трехл.40% 0.5л",
    "3417627": "Коньяк РОССИЙСК.ДАГЕСТАН пятил.40% 0.5л",
    "3417823": "Напит.ОАЗИС МОХИТО сл/град.негаз12% 0.5л",
    "3417843": "Виски ДЖИМ БИМ Бурбон 40% 0.5л",
    "3420243": "Водка МЕДОФФ ЛЮКС 40% 0.25л",
    "3420245": "Водка МЕДОФФ ПЛАТИНУМ 40% 0.5л",
    "3420251": "Водка НА БЕРЕЗ.БРУНЬКАХ ОРИГИН.40% 0.25л",
    "3420714": "Водка ТРИ КАПЛИ 40% 0.5л",
    "3420716": "Водка БРЯНСК ЛЮКС ОСОБАЯ новая 40% 0.5л",
    "3421054": "Водка РУССКИЙ СТАНДАРТ 40% 0.7л",
    "3421136": "Коньяк СТАРЫЙ КЕНИГС.Росс.5лет40% 0.375л",
    "3421437": "Настойка КАЗ.ДАР МЕД.С ПЕРЦ.гор.40% 0.5л",
    "3421438": "Настойка КАЗ.ДАР СТЕПНАЯ гор.40% 0.5л",
    "3422019": "Коньяк ПЯТЬ ЗВЕЗДОЧЕК росс.5лет 40% 0.5л",
    "3422494": "Джин ДЖЕЙМС ЛОНГЛИ ЛОНДОНС.38% ст/б 0.7л",
    "3424055": "Вино ПОР.МАРТ.ФАЙН РУБИ кр.лик.19% 0.75л",
    "3424076": "Коньяк ПЯТЬ ЗВЕЗДОЧЕК рос.5лет 40% 0.5л",
    "3425634": "Виски ГРАНТС 8лет 40% п/у 0.7л",
    "3426198": "Коньяк СТАРЕЙШИНА росс.5лет 40% 0.25л",
    "3426297": "Водка НА БЕРЕЗ.БРУН.ОРИГ.особ.40% 0.5л",
    "3426594": "Водка НАРОДНАЯ ВОДКА 40% 0.5л",
    "3426676": "Коньяк СТАР.ГВАРДИЯ рос.пятилет.40% 0.5л",
    "3426680": "Джин ВАЙТ ЛЕЙС 40% ст/б 0.5л",
    "3426714": "Водка ХОРТ.СЕРЕБР.ПРОХЛАДА ОСОБ.40% 0.5л",
    "3426717": "Водка ХОРТ.СЕРЕБР.ПРОХЛАДА ОСОБ.40% 0.7л",
    "3426718": "Водка ХОРТИЦА ПЛАТИНУМ 40% 0.5л",
    "3426720": "Виски ОКЕНТОШАН АМЕРИК.ОАК 40% п/у 0.7л",
    "3427180": "Водка ХОРТИЦА ПЛАТИНУМ 40% 0.7л",
    "3427274": "Коньяк ВЕЛИКАЯ ДИНАСТИЯ пятилет.40% 0.5л",
    "3427477": "Нап.ПОРТВЕЙН КРАСНЫЙ АЛУШТА вин.кр.0.75л",
    "3427481": "Нап.МАДЕРА КРЫМСКАЯ вин.бел.19% 0.75л",
    "3428594": "Водка ХОРТИЦА СЕР.ПРОХЛАДА особ.40% 1.0л",
    "3428665": "Виски ВИЛЬЯМ ЛОУСОНС 40% 0.7л",
    "3428832": "Коньяк ЗОЛОТ.РЕЗЕРВ росс.5лет 42% 0.25л",
    "3429067": "Вино С ПЛОДАМИ АБРИКОСА пл.сл.12% 0.7л",
    "3429070": "Нап.БУШМИЛЗ ХАНИ спирт.ирланд.35% 0.7л",
    "3429826": "Нап.ПОРТВ.БЕЛ.АЛУШТА вин.бел.17% 0.75л",
    "3430982": "Текила ТРЕС СОМБРЕРОС БЕЛ.38% 0.7л+стак.",
    "3431063": "Водка СТОЛИЧНАЯ СЕВЕР СПЕЦ.МЯГ.40% 0.5л",
    "3431526": "Коньяк НАYASY армянский 3года 40% 0.5л",
    "3431925": "Водка ПЕРВАК ДОМАШН.ПШЕН.особ.40% 0.5л",
    "3431965": "Настойк.МЕДОВУХА ГРЕЧ.гор.ар.мед.40%0.5л",
    "3432646": "Водка ТЕЛЬНЯШКА 40% 0.5л",
    "3433500": "Водка НА БЕРЕЗ.БРУН.ОРИГ.особ.40% 0.375л",
    "3433794": "Текила РАНЧО ВЬЕХО ГОЛД 38% 0.7л",
    "3434767": "Коньяк FAT.OLD BARREL рос.5л.40% п/у0.5л",
    "3434980": "Настойка СТАРКА горькая 40% 0.5л",
    "3435436": "Бурбон УАЙЛД ТЕКИ-81 40,5% 0.7л",
    "3435605": "Коньяк СТОЛИЧНЫЙ рос.пятилет.40% 0.5л",
    "3435607": "Виски БУШМИЛ ОРИДЖИНАЛ купаж.40% 0.5л",
    "3435609": "Напиток РОУСОНС РЕЗЕРВ висковый 40% 0.7л",
    "3435791": "Водка ПЬЯТНИЦА ДОБРАЯ 40% 0.5л",
    "3436177": "Нап.FINLAND.REDB.сп.вк.клюквы 37,5% 0.5л",
    "3436179": "Нап.FINLAND.CRANB.сп.вк.клюкв.37,5% 0.5л",
    "3436726": "Водка ГРАФИНЯ ЯБЛОНСКАЯ мягкая 40% 0.5л",
    "3437694": "Водка ПУТИНКА ВЕЗДЕХОД клас.40% 0.5л",
    "3438353": "Коньяк HENNESSY VSOP 40% п/у 0.5л",
    "3438427": "Коньяк ПЯТИЛЕТНИЙ ХАЙАСИ 40% 0.5л",
    "3438544": "Нап.ВЕРМУТ МАРТИАМО БЬЯНКО вин.15% 0.5л",
    "3438648": "Коньяк КВС ПЯТЬ ЗВЕЗ.росс.5лет 40% 0.25л",
    "3439072": "Джин GREEN STONE 40% 0.5л",
    "3439740": "Коньяк ДУГЛАДЗЕ груз.5лет 40% 0.5л",
    "3440186": "Вино КАГОР ГЕЛЕНДЖИКА кр.слад.стол.0.75л",
    "3441206": "Водка ХЛЕБНЫЙ ДАР ПШЕНИЧНАЯ 40% 0.5л",
    "3441390": "Коньяк ДИВИН КВИНТ 3года 40% 0.5л",
    "3442744": "Настойка МЕДОВУХА МЕД/ИМБ.гор.40% 0.5л",
    "3442894": "Водка ХОРТИЦА СЕРЕБ.ПРОХ.особ.40% 0.375л",
    "3442923": "Водка ХЛЕБ.ДАР НА ПРОРОЩ.ЗЕРНЕ 40% 0.5л",
    "3442925": "Виски JW BLACK LABEL 40% 12л п/у 0.5л",
    "3443259": "Водка ЗИМ.ДЕР.НА СОЛ.СП.АЛЬФА 40% 0.5л",
    "3443260": "Водка СОЛН.ДЕР.НА СОЛ.СП.АЛЬФА 40% 0.5л",
    "3443595": "Виски JW BLACK LABEL 12лет п/у 40% 0.7л",
    "3445905": "Коньяк КРЕМЛЕВСКИЙ росс.3лет 40% 0.5л",
    "3446573": "Водка ГОСТТМ МЯГКАЯ 40% 0.5л",
    "3447758": "Ром BACARDI CARTA BLANCA 40% 0.5л",
    "3447762": "Ром BACARDI CARTA NEGRA 40% 0.7л",
    "3451685": "Водка АРХАНГЕЛ.СЕВЕР.ВЫДЕРЖКА 40% 0.5л",
    "3452736": "Напиток ЕЖЕВИЧКА десертный 12% 0.5л",
    "3452739": "Наливка МОРОШКОВАЯ 18% 0.5л",
    "3452741": "Настойка РЯБИНА ЧЕРНОПЛОД.слад.16% 0.5л",
    "3453446": "Настойка КАПИТАН.РОМ ГОЛД горьк.40% 0.5л",
    "3455128": "Ром БАКАРДИ КАРТА БЛАНКА 40% 2х0.5л",
    "3455130": "Виски ВИЛЬЯМ ЛОУСОНС 40% 2х0.5л",
    "3455251": "Коньяк РОССИЙСКИЙ 3 звезды 40% 0.5л",
    "3456165": "Ром КАПИТАН МОРГАН ямайский 40% 0.5л",
    "3461729": "Водка Праздничная 0,7л 40% бутылка",
    "3461780": "Виски MACALLAN FINE OAK 12Y п/у 40% 0.5л",
    "3462547": "Настойка СОЛН.ДЕРЕВ.БАРСК.сл.19% 0.5л",
    "3462548": "Настойка СОЛН.ДЕР.Клюква слад.19% 0.5л",
    "3462550": "Настойка СОЛН.ДЕР.Бочк.горьк.36,6% 0.5л",
    "3462551": "Настойка СОЛН.ДЕР.Мед/перц.гор36,6% 0.5л",
    "3462765": "Бальзам ОХОТНИЧЬИ ПРОСТОРЫ 40% кер.0.5л",
    "3462771": "Вино АМАР.ПИНК МОСКАТ.игр.роз.сл.0.75л",
    "3463334": "Водка БЕЛАЯ СИЛА 40% 0.5л",
    "3465731": "Напит.спирт.JIM BEAM APPLE 35% 0.7л",
    "3466660": "Нап.вин.SANTA SANYTA VERM.BIAN.10% 1л",
    "3467663": "Водка ЧИЖИК 40% 0.5л",
    "3468138": "Водка ПЕРЕПЕЛКА ДЕРЕВЕНСКАЯ 40% 0.5л",
    "3468793": "Водка ПЕРЕПЕЛКА ФЕРМЕРСКАЯ особ.40% 0.5л",
    "3470475": "Водка ТАЛКА СИБИР.КЕДР особ.40% 0.5л",
    "3470476": "Водка ТАЛКА СИБИР.КЕДР особ.40% 0.25л",
    "3470883": "Ром КАПИТАН МОРГАН УАЙТ кариб.40% 0.5л",
    "3470884": "Кокт.нап.виск.РОУСОНС РЕЗЕРВ 40% 0.5л",
    "3471029": "Ром КАПИТАН МОРГАН УАЙТ кариб.40% 0.7л",
    "3471998": "Водка СПЕЦПАЕК МОРСКОЙ 40% 0.5л",
    "3472150": "Наст.СИББИТТЕР КЕДР.ВЫДЕРЖ.гор.38% 0.5л",
    "3472151": "Наст.СИББИТТЕР СИБ.РАЗНОТР.гор.38% 0.5л",
    "3472315": "Нап.спирт.ВИЛЬЯМ ЛОУС.СУП.СПАЙС.35% 0.7л",
    "3472359": "Виски ОЛД КЛАРК купажированный 40% 0.5л",
    "3472490": "Коньяк ГАЛАВАНИ груз.8лет 40% 0.5л",
    "3472494": "Коньяк ВЕЛ.МОУРАВИ груз.5лет 40% 0.5л",
    "3473046": "Вино АБРИКОС.РАЙ плод.п/сл.12% 1.0л",
    "3473747": "Коньяк COURVOISIER VS 40% 0.7л+2бокала",
    "3473751": "Виски FAMOUS GROUSE 40% 0.7л +2 бокала",
    "3473973": "Нап.OAKHEART ORIGIN.на осн.рома 35% 0.5л",
    "3473974": "Нап.OAKHEART ORIGIN.на осн.рома 35% 0.7л",
    "3474586": "Виски WILLIAM LAWSONS 40% 0.2л",
    "3474768": "Виски J&B RARE шотл.купажир.40% п/у 0.7л",
    "3475449": "Коньяк АРМЯНСКИЙ 3года 40% 0.25л",
    "3475451": "Виски СТРОНГХОЛД купаж.40% 0.25л",
    "3475452": "Коньяк АРАХТАН армян.7лет 40% п/у 0.5л",
    "3475468": "Водка СТОЛИЧНАЯ 40% +2стопки п/у 0.5л",
    "3476051": "Виски БЭЛЛС ОРИДЖИНАЛ 40% 2х0.5л",
    "3476084": "Водка СИНЕНЬКАЯ 40% 0.5л",
    "3476311": "Ликер КАЛУА кофейный 20% 1.0л",
    "3476410": "Нап.вин.ДЕЛАСИ КОСМОСИТИ 12% 1.0л",
    "3476693": "Виски ДЖ.УОКЕР РЭД ЛЕЙБЛ 40% 0.7л+стакан",
    "3476695": "Виски УАЙТ ХОРС 40% 2х0.5л",
    "3476903": "Водка МОРОША ур/мяг.№1 40% 0.25л",
    "3477026": "Виски JAMESON 40% п/у 0.7л+2бокала",
    "3477028": "Коньяк HENNESSY VS 40% 0.7л+2бок.п/у",
    "3477066": "Коньяк АЙК армян.7лет.40% 0.5л",
    "3477127": "Водка РУССКАЯ ВАЛЮТА PLATINUM 40% 0.1л",
    "3477128": "Водка РУССКАЯ ВАЛЮТА PLATINUM 40% 0.375л",
    "3477418": "Виски ЧИВАС РИГАЛ 12лет 40% 0.7л+2бокала",
    "3477726": "Наст.БИЛЛИ БОБ ТЕЙСТ ОФ РОМ п/сл.40%0.5л",
    "3477965": "Настойка РЯБИНА НА КОНЬЯКЕ слад.18% 0.5л",
    "3477966": "Настойка ВИШНЯ НА КОНЬЯКЕ слад.18% 0.5л",
    "3478194": "Водка особая Хортиця Серебр.прохл.0,25л",
    "3478686": "Водка ЛЕГКАЯ ВОДКА ВОЗДУХ особ.40% 0.5л",
    "3479240": "Водка БАЗАРВОКЗАЛ ЯРОСЛАВ.КУПАЖ 40% 0.5л",
    "3479243": "Водка БОРЩЕВКА С ХОЛОДКОМ особ.40% 0.5л",
    "3479461": "Нап.вин.СО ВК.КЛЮКВА НА КОНЬЯКЕ 14% 0.5л",
    "3479462": "Нап.вин.СО ВК.СЛИВА НА КОНЬЯКЕ 14% 0.5л",
    "3479463": "Нап.вин.СО ВК.ВИШНЯ НА КОНЬЯКЕ 14% 0.5л",
    "3479466": "Водка ХАСКИ ICE 40% 0.5л",
    "3481856": "Джин GIN GREEN WITCH 45% 0.5л",
    "3482343": "Водка ЗЕЛЕНАЯ МАРКА КЕДР.особ.40% 0.1л",
    "3482682": "Нап.спирт.ХЛЕБНИК 40% 0.5л",
    "3482734": "Настойка АБСЕНТ АБСОЛВЕНТ гор.70% 0.5л",
    "3482993": "Водка СТУЖА КЕДРОВАЯ 40% 0.5л",
    "3483838": "Коньяк FRANCOIS BATIST рос.5лет.40% 0.5л",
    "3484252": "Настойка DON CHIKU BL.гор.вк.тек40% 0.5л",
    "3484520": "Водка ЖАВОРОНКИ КЛАССИЧЕСКАЯ 40% 0.5л",
    "3485671": "Ликер БЕЛУГА ХАНТИНГ ТРАВ.дес.40% 0.5л",
    "3488292": "Вино ЯБЛОКО СО СЛИВОЙ фр.cл.12% 0.7л",
    "3489326": "Коньяк САЯТ НОВА ПЯТЬ ЗВЕЗД арм.40% 0.5л",
    "3490643": "Водка ЗИМ.ДЕР.МОЖЖЕВЕЛОВАЯ 40% 0.5л",
    "3490994": "Водка СТУЖА ЛЕДЯНАЯ 40% 0.5л",
    "3494943": "Ром ГАВАНА КЛУБ АНЬЕХО ЭСПЕС.40% 0.7л",
    "3495262": "Водка СИББИТ.СИБИР.СПЕЦИАЛ.40% 0.5л",
    "3495721": "Водка ЗИМ.ДЕР.ТАЕЖНАЯ 40% 0.5л",
    "3497460": "Водка БЕЛ.БЕРЕЗКА ЗОЛОТАЯ 40% 0.5л",
    "3498443": "Коньяк СТАРЕЙШИНА IN SINGLE BARREL рос.7",
    "3501785": "Виски JOHNNIE WALKER RED LABEL 40% 0.7л",
    "3504071": "Виски WILLIAM LAWSONS 40% 0.5л",
    "3504072": "Водка KREMLIN AWARD CLASSIC 40% 0.5л",
    "3504399": "Ликер БЕЛУГА ХАНТИНГ ЯГОД.дес.38% 0.5л",
    "3504727": "Настойка ЗУБРОВКА ЛЕГЕНД.гор.40% 0.5л",
    "3505473": "Виски ВИЛЬЯМ ЛОУСОНС 40% п/у 2х0.5л",
    "3600783": "Водка ЗИМНЯЯ ДОРОГА 40% 0.25л",
    "3601040": "Вино СЕВАСТ.ИГР.КРЫМСКОЕ роз.п/сл.0.75л",
    "3601210": "Водка ГЕОРГИЕВСКАЯ 40% 0.5л",
    "3602118": "Аперитив СТЕПНОЙ КОНЬ 18% 0.5л",
    "3602269": "Водка КАЗЕНКА 40% 0.375л",
    "3602364": "Коньяк ПЯТЬ ЗВЕЗДОЧЕК рос.40% 0.5л",
    "3602801": "Настойка КОНЬЯЧНАЯ с аром.рябин.18% 0.5л",
    "3602807": "Настойка ЕГЕРСКАЯ ТАЕЖ.ТР.п/сл 35% 0.5л",
    "3602808": "Настойка КОНЬЯЧНАЯ с аром.брусн.18% 0.5л",
    "3602826": "Виски ВИЛЬЯМ ЛОУСОНС п/у 40% 0.7л",
    "3602960": "Водка МАЙКОПСКАЯ 40% 0.5л",
    "3602961": "Водка МАЙКОПСКАЯ 40% 0.25л",
    "3602973": "Водка РОДИМАЯ оригинальная 40% 0.5л",
    "3603567": "Водка ФИННОРД 40% 0.25л",
    "3603933": "Коньяк АРМЯНСКИЙ АРАХТАН 7л 40% п/у 0.5л",
    "3603934": "Коньяк АРМЯНСКИЙ 3года 40% 0.5л",
    "3603935": "Коньяк АРМЯНСКИЙ 3года 40% 0.25л",
    "3603958": "Коньяк ЗОЛОТОЙ РЕЗЕРВ рос.5л.40% 0.5л",
    "3603959": "Коньяк ЗОЛОТОЙ РЕЗЕРВ рос.5л.40% 0.25л",
    "3603960": "Коньяк ЗОЛОТОЙ РЕЗЕРВ рос.5л.40% 0.1л",
    "3603975": "Коньяк СТАРЫЙ КЕНИГСБЕРГ 4лет.40% 0.1л",
    "3604202": "Вино РИУНИТЕ ЛАМБРУСКО игр.к.п/сл 0.75л",
    "3604207": "Вино РИУНИТЕ ЛАМ.РОЗЕ игр.роз.п/сл 0.75л",
    "3604454": "Настойка ПЕРЦОВОЧКА с перч.гор.35% 0.25л",
    "3604457": "Коньяк ЧЕРНОМОРСКИЙ 5зв.5лет.40% 0.5л",
    "3604665": "Джин ВАЙТ ЛЕЙС 40% 0.7л",
    "3604736": "Водка БАТЬКОВА БЕЛОВЕЖСКАЯ 40% 0.5л",
    "3604737": "Водка БАТЬКОВА 40% 0.5л",
    "3604832": "Коньяк ПЯТЬ ЗВЕЗДОЧЕК рос.5л.42% 0.1л",
    "3605073": "Коньяк ФРАНЦУЗ.СТАНДАРТ КВ росс.40% 0.5л",
    "3605227": "Коньяк ПЯТЬ ЗВЕЗДОЧЕК рос.5л.40% 0.1л",
    "3605701": "Настойка BURNED BARREL гор.ар.виски 0.5л",
    "3605732": "Ликер ЛИМОНЧЕЛЛО ДЕЛЬ КОНТЕ дес.25% 0.5л",
    "3606482": "Ликер САМБУКА ИСЕО 38% 0.5л",
    "3607070": "Коньяк ПЯТЬ ЗВЕЗДОЧЕК росс.пят.40% 0,25л",
    "3607071": "Коньяк ТРИ ЗВЕЗДОЧКИ трех.росс.40% 0,25л",
    "3607409": "Коньяк РОССИЙСКИЙ Пять звезд.40% 0.1л",
    "3608050": "Настойка ТРИ СТАРИКА гор.40% 0.1л",
    "3608065": "Водка СОРМОВСКАЯ ЛЮКС 40% 0.1л",
    "3608066": "Водка ХОРТИЦЯ АЙС особая 40% 0.5л",
    "3608096": "Коньяк ГАЛАВАНИ груз.5лет.40% 0.5л",
    "3608140": "Коньяк КОКТЕБЕЛЬ рос.5лет 40% 0.5л",
    "3608306": "Водка ЧИСТЫЕ РОСЫ 40% 0.5л",
    "3608347": "Нап.вин.ФИАНТИ.ВЕРМУТ БЬЯНКО 12% 1.0л",
    "3608622": "Нап.вин.ВЕРМУТ САНТАНЕЛЛИ БЕЛЫЙ 0.5л",
    "3608931": "Водка БОРЩЕВКА особ.40% 0.5л",
    "3608986": "Настойка БРЯНСКАЯ ПЕРЦОВАЯ гор.35% 0.1л",
    "3609008": "Коньяк САЯТ НОВА арм.5л.40%п/у 0.5л+2бок",
    "3609855": "Водка №1 40% 0.5л",
    "3610106": "Наб.Виски БЭЛЛС ОРИДЖИНАЛ 40% 1.0л+стак.",
    "3610113": "Нап.сп.КАП.МОРГАН ЗОЛОТ.35% п/у+ст 1.0л",
    "3610122": "Виски УАЙТ ХОРС 40% п/у 1.0л +стакан",
    "3610155": "Вино МАРТИНИ НЕРО игр.сл.кр.8% 0.75л",
    "3610426": "Виски AUCHENT.AM.OAK шотл.40%п/у0.7л+2кр",
    "3610644": "Виски ВИЛЬЯМ ЛОУСОНС 40% 1л",
    "3610645": "Виски ВИЛЬЯМ ЛОУСОНС 40% 0.7л",
    "3610870": "Вино ГАНЧА МОСКАТО РОЗЕ игр.р.сл7% 0.75л",
    "3610914": "Ром БАКАРДИ КАРТА НЭГРА п/у 0.7л+дин.вст",
    "3611030": "Виски ДЖИМ БИМ бурбон 40% 0.7л+2 стакан",
    "3611071": "Водка ЗУБРОВКА КЛАССИЧЕСКАЯ 40% 0.5л",
    "3617525": "Настойка КАПИТАН.СО ВК.РОМ.ГОЛД п/сл0.5л",
    "3618702": "Виски БАЛЛАНТАЙЗ ФАЙНЕСТ 40%п/у0.7л+2бок",
    "3620216": "Нап.вин.КАГОР МОНАСТЫРСКИЙ САД 16% 0.7л",
    "3620361": "Бренди ДЕРБЕНТСКАЯ КРЕПОСТЬ 37,5% 0.5л",
    "3620380": "Коньяк SHUSTOFF рос.4лет.40% 0.5л",
    "3620813": "Коньяк АВШАР армян.пятилет.40% 0.5л",
    "3620840": "Настойка СИББИТ.СИБИР.ХРЕН.гор.38% 0.5л",
    "3621785": "Виски SCOTTISH LAND шотл.купаж.40% 0.05л",
    "3621786": "Ликер AMARETTO VITTONE дес.25% 0.05л",
    "3621787": "Нап.спирт.FERNET VITTONE 40% 0.05л",
    "3623048": "Водка БОГАТСТВО СИБИРИ СЕРЕБР.40% 0.5л",
    "3623097": "Настойка САМОГОНОВЪ БОЧКАРЬ гор.41% 0.5л",
    "3623394": "Бренди M.TORRES 5 СОЛ.РЕЗ.38% 0.5л",
    "3624845": "Нап.вин.САНТО СТЕФАНО газ.р.п/сл8% 0.75л",
    "3625237": "Виски ВИЛЬЯМ ЛОУСОНС 40% 3х0.5л",
    "3626501": "Водка УРОЖАЙ на расторопше 40% 0.5л",
    "3627345": "Коньяк АРАРАТ 5зв.армянский 40% 0.05л",
    "3627750": "Водка ДОБРЫЙ МЕДВЕДЬ 40% 0.25л",
    "3627800": "Водка ЦЕЛЬСИЙ КЛАССИК 0.2л",
    "3628713": "Нап.CAPT.MOR.SPIC.GOLD осн.ром35% 2х0.5л",
    "3630356": "Нап.вин.АКУРА БЕЛ.вк.сливы сл.8,5% 0.75л",
    "3631817": "Водка БЕЛОРУССКАЯ ЛЮКС 40% 0.5л",
    "3632316": "Нап.вин.SANTA SANYTA VERM.ROSSO сл.1.0л",
    "3632746": "Вино ШАТО ТАМАНЬ РЕЗ.игр.роз.брют 0.75л",
    "3633355": "Виски SCOTCH TERRIER 3лет.40% 0.5л",
    "3634170": "Настойка АРХАНГЕЛ.ЧЕСНОЧ.С ПЕРЦ.0.5л",
    "3636391": "Нап.вин.ROSA DI ANGELO газ.слад.0.75л",
    "3636471": "Граппа GRAP.DI MOSC.GLI IMPERIALI 0.5л",
    "3637388": "Ром БАКАРДИ КАРТА БЛАНКА 40% 0.7л+стакан",
    "3637988": "Водка ХЛЕБНАЯ ПОЛОВ.ПШЕН.МЯГ.40% 0.45л",
    "3637989": "Водка ХЛЕБНАЯ ПОЛОВ.РЖАН.МЯГ.40% 0.45л",
    "3637990": "Водка ЛЕГКАЯ ВОЗДУХ АЙС 40% 0.5л",
    "3639717": "Виски BILL MCLEAN трад.купаж.40% 0.05л",
    "3640799": "Напиток КОНЬЯК ДЖИВАН с мед.креп40% 0.5л",
    "3640820": "Напиток КОНЬЯК ДЖИВАН с кор.креп40% 0.5л",
    "3641020": "Коньяк СТАРЕЙШИНА рос.трехл.40% 0.5л",
    "3641346": "Вино ПОРТВЕЙН БЕЛЫЙ АЛУШТА лик.б.0.75л",
    "3641347": "Вино ПОРТВЕЙН КРАСНЫЙ АЛУШТА лик.к.0.75л",
    "3641348": "Вино МУСКАТ БЕЛ.КРАСН.КАМНЯ лик.б.0.75л",
    "3641349": "Вино ЧЕРНЫЙ ДОКТОР МАССАНДРА лик.к.0.75л",
    "3642065": "Водка СЯБРЫ НА БЕР.ПОЧКАХ особ.40% 0.5л",
    "3642266": "Виски СИНГЛТОН.ВИСКОК.ДАФФТ.40% 0.5л",
    "3645787": "Наст.НАП.ВИЛ.ЛОУС.СУП.СП.ОСН.ВИС.35%0.5л",
    "3647616": "Коньяк САЯТ НОВА 7 ЛЕТ МАР.п/у 0.5л+2бок",
    "3647650": "Коньяк ПОЗДРАВИТЕЛ.армян.5лет 40% 0.5л",
    "3648323": "Коньяк SHUSTOFF пятилет.п/у 0.5л+стакан",
    "3648910": "Нап.спирт.ТЕКИЛА ОЛЬМ.БЕЛ.38%п/у 0.7л+2б",
    "3648911": "Нап.спирт.OAKHEART ORIGIN.35%п/у 0.7л+ст",
    "3649291": "Ликер БЕХЕРОВКА дес.38% п/у 0.7л+2чашки",
    "3650425": "Коньяк ДРЕВ.ЭРИВАНЬ арм.5лет.40% 0.5л",
    "3651850": "Виски LABEL 5 40% 0.2л",
    "3651880": "Вино МУСКАТЕЛЬ МАССАНДРА РОЗ.лик.0.75л",
    "3651895": "Вино МАДЕРА КРЫМСКАЯ бел.лик.0.75л",
    "3652205": "Шампанское КАРТ ДОР ДР.б.бр.12%п/у 0.75л",
    "3652398": "Виски LABEL 5 40% 0.7л",
    "3652407": "Виски LABEL 5 40% 0.35л",
    "3653523": "Настойка СИББИТ.С.МЕД С П.38%п/у 0.5л+кр",
    "3654717": "Водка РУССКАЯ ВАЛЮТА 38% 0.5л",
    "3656964": "Водка РУССКАЯ ВАЛЮТА 38% 0.25л",
    "3656966": "Водка ПИТЕЙНЫЙ ДОМ ДОМАШНЯЯ 40% 0.5л",
    "3660054": "Вино КАГОР ПАРТЕНИТ лик.кр.0.75л",
    "3661859": "Водка БЕЛОВЕЖСКАЯ ЛЕДЯНАЯ ПРЕМ.40% 0.5л",
    "3661949": "Водка ГЖЕЛКА 40% 0.5л",
    "3662170": "Нап.вин.САН.СТЕФ.ВЕРМ.БЬЯН.особ.сл.1.0л",
    "3662212": "Нап.ПОЛУГАР №4 МЕД/ПЕРЕЦ спир.38,5% 0.5л",
    "3662870": "Вино КАГОР PASTORAL ликерное кр.0.75л"
  }
]